Workbook

Sheet Ingresos
A2: VERDANT STONE · Ingresos por Proyecto
A3: Mes / Año:
A6: # | B6: Cliente / Proyecto | C6: Ciudad | D6: Contrato ($) | E6: Cobrado ($) | F6: Pendiente ($) | G6: Estado
A7: 1 | F7: =IF(D7="","",D7-E7)
A8: 2 | F8: =IF(D8="","",D8-E8)
A9: 3 | F9: =IF(D9="","",D9-E9)
A10: 4 | F10: =IF(D10="","",D10-E10)
A11: 5 | F11: =IF(D11="","",D11-E11)
A12: 6 | F12: =IF(D12="","",D12-E12)
A13: 7 | F13: =IF(D13="","",D13-E13)
A14: 8 | F14: =IF(D14="","",D14-E14)
A15: 9 | F15: =IF(D15="","",D15-E15)
A16: 10 | F16: =IF(D16="","",D16-E16)
A17: TOTAL DEL MES | D17: =SUM(D7:D16) -> 0 | E17: =SUM(E7:E16) -> 0 | F17: =SUM(F7:F16) -> 0
A19: Azul = datos a ingresar · Negro = calculado automáticamente · Estado: Cobrado / Pendiente / 50% Depósito

Sheet Materiales
A2: VERDANT STONE · Gastos de Materiales
A3: Mes / Año:
A6: # | B6: Material / Descripción | C6: Proyecto | D6: Proveedor | E6: Cant. | F6: Precio Unit. ($) | G6: Total ($)
A7: 1 | G7: =IF(E7="","",E7*F7)
A8: 2 | G8: =IF(E8="","",E8*F8)
A9: 3 | G9: =IF(E9="","",E9*F9)
A10: 4 | G10: =IF(E10="","",E10*F10)
A11: 5 | G11: =IF(E11="","",E11*F11)
A12: 6 | G12: =IF(E12="","",E12*F12)
A13: 7 | G13: =IF(E13="","",E13*F13)
A14: 8 | G14: =IF(E14="","",E14*F14)
A15: 9 | G15: =IF(E15="","",E15*F15)
A16: 10 | G16: =IF(E16="","",E16*F16)
A17: TOTAL MATERIALES | G17: =SUM(G7:G16) -> 0

Sheet Mano de Obra
A2: VERDANT STONE · Mano de Obra / Subcontratistas
A3: Mes / Año:
A6: # | B6: Persona / Empresa | C6: Proyecto | D6: Días | E6: Tarifa/Día ($) | F6: Total ($) | G6: Pagado
A7: 1 | F7: =IF(D7="","",D7*E7)
A8: 2 | F8: =IF(D8="","",D8*E8)
A9: 3 | F9: =IF(D9="","",D9*E9)
A10: 4 | F10: =IF(D10="","",D10*E10)
A11: 5 | F11: =IF(D11="","",D11*E11)
A12: 6 | F12: =IF(D12="","",D12*E12)
A13: 7 | F13: =IF(D13="","",D13*E13)
A14: 8 | F14: =IF(D14="","",D14*E14)
A15: TOTAL MANO DE OBRA | F15: =SUM(F7:F14) -> 0

Sheet Resumen
A2: VERDANT STONE · Resumen Financiero del Mes
A3: Mes / Año:
A5: INGRESOS
A6: Total Contratos del Mes | B6: =Ingresos!D17 -> 0
A7: Total Cobrado | B7: =Ingresos!E17 -> 0
A8: Total Pendiente de Cobro | B8: =Ingresos!F17 -> 0
A10: COSTOS
A11: Total Materiales | B11: =Materiales!G17 -> 0
A12: Total Mano de Obra | B12: ='Mano de Obra'!F15 -> 0
A13: Total Costos del Mes | B13: =B11+B12 -> 0
A15: MARGEN
A16: Margen Neto (Ingresos Cobrados - Costos) | B16: =B7-B13 -> 0
A17: Margen % (Neto ÷ Cobrado × 100) | B17: =IF(B7=0,"-",B16/B7) -> -
A19: Meta sugerida para proyectos premium: Margen ≥ 40%
A20: Azul = ingresar en cada hoja · Negro = calculado · Verde = traído de otra hoja
